{
  "app_name": "inventory",
  "src_hash": "c700ffd7ab7201176da5f973671654f0c241b438",
  "src_tag": "",
  "src_branch": "nightly",
  "patternfly_dependencies": ["@patternfly/patternfly@4.70.2","@patternfly/react-charts@6.13.3","@patternfly/react-core@4.88.0","@patternfly/react-icons@4.7.22","@patternfly/react-table@4.19.24","@patternfly/react-tokens@4.9.22"],
  "travis": {
    "event_type": "cron",
    "build_number": "4436",
    "build_web_url": "https://travis-ci.com/RedHatInsights/insights-inventory-frontend/builds/213356854"
  }
}
